cdps/__init__.py
cdps/__main__.py
cdps/boostrap.py
cdps/cdps_server.py
cdps/config.py
cdps/entrypoint.py
cdps/state.py
cdps/cli/__init__.py
cdps/cli/cli_entry.py
cdps/cli/cli_gendefault.py
cdps/cli/cli_init.py
cdps/cli/cli_run.py
cdps/cli/cli_version.py
cdps/console/__init__.py
cdps/console/cdps.py
cdps/constants/__init__.py
cdps/constants/core_constant.py
cdps/plugin/__init__.py
cdps/plugin/events.py
cdps/plugin/manager.py
cdps/plugin/thread.py
cdps/resources/default_config.yml
cdps/utils/__init__.py
cdps/utils/file_util.py
cdps/utils/lazy_item.py
cdps/utils/level.py
cdps/utils/line.py
cdps/utils/logger.py
cdps/utils/misc_util.py
cdps/utils/pack.py
cdps/utils/resources_util.py
cdps/utils/version.py
cdps/utils/yaml_data_storage.py
cdps-1.0.18.dist-info/LICENSE
cdps-1.0.18.dist-info/METADATA
cdps-1.0.18.dist-info/WHEEL
cdps-1.0.18.dist-info/entry_points.txt
cdps-1.0.18.dist-info/top_level.txt
cdps-1.0.18.dist-info/RECORD
