Metadata-Version: 2.1
Name: cdps
Version: 1.0.18
Summary: Composite Disaster Prevention Server
Home-page: UNKNOWN
Author: ExpTechTW
Author-email: exptech.tw@gmail.com
License: UNKNOWN
Platform: UNKNOWN
Classifier: License :: OSI Approved :: GNU Affero General Public License v3 or later (AGPLv3+)
Classifier: Operating System :: OS Independent
Classifier: Programming Language :: Python
Classifier: Programming Language :: Python :: 3
Classifier: Programming Language :: Python :: 3.8
Classifier: Programming Language :: Python :: 3.9
Classifier: Programming Language :: Python :: 3.10
Classifier: Programming Language :: Python :: 3.11
Classifier: Programming Language :: Python :: 3.12
Requires-Python: >=3.8
License-File: LICENSE
Requires-Dist: pytz ==2024.1
Requires-Dist: ruamel.yaml ==0.18.6
Requires-Dist: ruamel.yaml.clib ==0.2.8
Requires-Dist: typing-extensions ==4.12.1
